{
  "hash": "66e048fe",
  "browserHash": "47391f73",
  "optimized": {
    "@vuepress/shared": {
      "src": "../../../../../../node_modules/.pnpm/registry.npmmirror.com+@vuepress+shared@2.0.0-beta.60/node_modules/@vuepress/shared/dist/index.js",
      "file": "@vuepress_shared.js",
      "fileHash": "9cf1d4a2",
      "needsInterop": false
    },
    "vue": {
      "src": "../../../../../../node_modules/.pnpm/registry.npmmirror.com+vue@3.2.47/node_modules/vue/dist/vue.runtime.esm-bundler.js",
      "file": "vue.js",
      "fileHash": "3c938ca8",
      "needsInterop": false
    },
    "vue-router": {
      "src": "../../../../../../node_modules/.pnpm/registry.npmmirror.com+vue-router@4.1.6_vue@3.2.47/node_modules/vue-router/dist/vue-router.esm-bundler.js",
      "file": "vue-router.js",
      "fileHash": "fc863e2b",
      "needsInterop": false
    }
  },
  "chunks": {
    "chunk-ORHQLNQL": {
      "file": "chunk-ORHQLNQL.js"
    },
    "chunk-ECJNC3UZ": {
      "file": "chunk-ECJNC3UZ.js"
    }
  }
}